FlickrPicDownload/__init__.py
FlickrPicDownload/helpers.py
FlickrPicDownload/login.py
flickrpicdownload-0.0.1.dist-info/METADATA
flickrpicdownload-0.0.1.dist-info/WHEEL
flickrpicdownload-0.0.1.dist-info/licenses/LICENSE.txt
flickrpicdownload-0.0.1.dist-info/RECORD
