Metadata-Version: 2.4
Name: FlickrPicDownload
Version: 0.0.1
Summary: Useful python package for downloading flickr images in different solution
Project-URL: Homepage, https://github.com/edwardkao6413/FlickrPicDownload
Project-URL: Issues, https://github.com/edwardkao6413/FlickrPicDownload/issues
Author-email: edwardkao6413 <edwardkao6413@gmail.com>
License:                     GNU GENERAL PUBLIC LICENSE
License-File: LICENSE.txt
Classifier: License :: OSI Approved :: GNU General Public License v3 (GPLv3)
Classifier: Operating System :: OS Independent
Classifier: Programming Language :: Python :: 3
Requires-Python: >=3.7
